t6logreader/__init__.py
t6logreader/t6logreader.py
T6LogReader-0.1.1.dist-info/LICENSE
T6LogReader-0.1.1.dist-info/METADATA
T6LogReader-0.1.1.dist-info/WHEEL
T6LogReader-0.1.1.dist-info/top_level.txt
T6LogReader-0.1.1.dist-info/RECORD
