Metadata-Version: 2.1
Name: T6LogReader
Version: 0.1.1
Summary: A Python module for reading and searching Plutonium T6 logs
Home-page: https://github.com/Yallamaztar/T6LogReader
Author: budiworld
Author-email: budi.world@yahoo.com
Classifier: Programming Language :: Python :: 3
Classifier: License :: OSI Approved :: MIT License
Classifier: Operating System :: OS Independent
Requires-Python: >=3.10
License-File: LICENSE
